covexclude/__about__.py
covexclude/__init__.py
covexclude/compat.py
covexclude/coverageprocessor.py
covexclude/driver.py
covexclude/filehashcache.py
covexclude/linecache.py
covexclude/plugin.py
pytest_cov_exclude-0.0.9.dist-info/DESCRIPTION.rst
pytest_cov_exclude-0.0.9.dist-info/METADATA
pytest_cov_exclude-0.0.9.dist-info/RECORD
pytest_cov_exclude-0.0.9.dist-info/WHEEL
pytest_cov_exclude-0.0.9.dist-info/entry_points.txt
pytest_cov_exclude-0.0.9.dist-info/metadata.json
pytest_cov_exclude-0.0.9.dist-info/top_level.txt
