Metadata-Version: 2.0
Name: pytest-cov-exclude
Version: 0.0.9
Summary: Pytest plugin for excluding tests based on coverage data
Home-page: https://github.com/mhallin/cov-exclude-py
Author: Magnus Hallin
Author-email: mhallin@fastmail.com
License: MIT
Keywords: cover,coverage,pytest,py.test,performance,speed
Platform: UNKNOWN
Classifier: Development Status :: 4 - Beta
Classifier: Intended Audience :: Developers
Classifier: License :: OSI Approved :: MIT License
Classifier: Operating System :: MacOS :: MacOS X
Classifier: Operating System :: POSIX
Classifier: Programming Language :: Python
Classifier: Programming Language :: Python :: 2.7
Classifier: Programming Language :: Python :: 3.3
Classifier: Programming Language :: Python :: 3.4
Classifier: Programming Language :: Python :: 3.5
Classifier: Programming Language :: Python :: Implementation :: CPython
Classifier: Programming Language :: Python :: Implementation :: PyPy
Classifier: Topic :: Software Development :: Testing
Requires-Dist: coverage (>=4.0.0,<5.0.0)
Requires-Dist: ujson (>=1.0,<2.0)
Provides-Extra: dev
Requires-Dist: pytest (>=2.8.0,<2.9.0); extra == 'dev'
Provides-Extra: dist
Requires-Dist: twine; extra == 'dist'
Requires-Dist: wheel; extra == 'dist'
